confidence_interval_tools/__init__.py
confidence_interval_tools/core/__init__.py
confidence_interval_tools/core/somecontent.py
confidence_interval_tools-0.1.7.dist-info/LICENSE
confidence_interval_tools-0.1.7.dist-info/METADATA
confidence_interval_tools-0.1.7.dist-info/WHEEL
confidence_interval_tools-0.1.7.dist-info/RECORD
