Metadata-Version: 2.1
Name: confidence-interval-tools
Version: 0.1.7
Summary: A small package for calculating drawing confidence intervals.
Home-page: https://gitlab.com/aufildelanuit/confidence-interval-tools
License: MIT
Keywords: data science,confidence intervals,graphing,extreme values
Author: Yohann OPOLKA
Author-email: yohann.opolka@gmail.com
Requires-Python: >=3.9,<4.0
Classifier: License :: OSI Approved :: MIT License
Classifier: Programming Language :: Python :: 3
Classifier: Programming Language :: Python :: 3.9
Classifier: Programming Language :: Python :: 3.10
Classifier: Programming Language :: Python :: 3.11
Classifier: Programming Language :: Python :: 3.12
Requires-Dist: matplotlib (>=3.0,<4.0)
Requires-Dist: numpy (>=1.0,<2.0)
Requires-Dist: pandas (>=2.0,<3.0)
Requires-Dist: scipy (>=1.10,<2.0)
Requires-Dist: seaborn (>=0.10,<0.11)
Project-URL: Repository, https://gitlab.com/aufildelanuit/confidence-interval-tools
